{"name":"Исход (Синодальный)","title":false,"cs":false,"cs2":false,"left":true,"red":null,"lines":[{"index":16,"settings":{"name":null,"title":null,"cs":null,"cs2":null,"left":null,"red":null,"lines":null,"parallels":["Исх.19:9","3.Цар.8:10-11","2.Пар.7:1"]}},{"index":1,"settings":{"name":null,"title":null,"cs":null,"cs2":null,"left":null,"red":null,"lines":null,"parallels":["Исх.18:25"]}},{"index":17,"settings":{"name":null,"title":null,"cs":null,"cs2":null,"left":null,"red":null,"lines":null,"parallels":["Втор.4:24","Втор.9:3","Евр.12:29"]}},{"index":18,"settings":{"name":null,"title":null,"cs":null,"cs2":null,"left":null,"red":null,"lines":null,"parallels":["Исх.34:28","Втор.9:9:18"]}},{"index":3,"settings":{"name":null,"title":null,"cs":null,"cs2":null,"left":null,"red":null,"lines":null,"parallels":["Ин.7:19"]}},{"index":4,"settings":{"name":null,"title":null,"cs":null,"cs2":null,"left":null,"red":null,"lines":null,"parallels":["Быт.31:45"]}},{"index":5,"settings":{"name":null,"title":null,"cs":null,"cs2":null,"left":null,"red":null,"lines":null,"parallels":["Чис.3:41"]}},{"index":7,"settings":{"name":null,"title":null,"cs":null,"cs2":null,"left":null,"red":null,"lines":null,"parallels":["Тов.5:1"]}},{"index":8,"settings":{"name":null,"title":null,"cs":null,"cs2":null,"left":null,"red":null,"lines":null,"parallels":["Евр.9:19-20"]}},{"index":10,"settings":{"name":null,"title":null,"cs":null,"cs2":null,"left":null,"red":null,"lines":null,"parallels":["Исх.33:20","Иез.1:26","Иез.10:1"]}},{"index":11,"settings":{"name":null,"title":null,"cs":null,"cs2":null,"left":null,"red":null,"lines":null,"parallels":["Исх.19:12","Исх.33:22"]}},{"index":14,"settings":{"name":null,"title":null,"cs":null,"cs2":null,"left":null,"red":null,"lines":null,"parallels":["Исх.31:2","Исх.35:30"]}}],"parallels":null}