{"name":"2я книга Царств (Еврейский)","title":false,"cs":false,"cs2":false,"left":false,"red":null,"lines":[{"index":1,"settings":{"name":null,"title":null,"cs":null,"cs2":null,"left":null,"red":null,"lines":null,"parallels":["1.Цар.27:6","1.Цар.30:17"]}},{"index":2,"settings":{"name":null,"title":null,"cs":null,"cs2":null,"left":null,"red":null,"lines":null,"parallels":["Быт.37:34","1.Цар.4:12","Иов.2:12"]}},{"index":18,"settings":{"name":null,"title":null,"cs":null,"cs2":null,"left":null,"red":null,"lines":null,"parallels":["Быт.49:8","Нав.10:13"]}},{"index":4,"settings":{"name":null,"title":null,"cs":null,"cs2":null,"left":null,"red":null,"lines":null,"parallels":["2.Цар.4:10"]}},{"index":20,"settings":{"name":null,"title":null,"cs":null,"cs2":null,"left":null,"red":null,"lines":null,"parallels":["1.Цар.17:23","Суд.11:34","Суд.14:19"]}},{"index":21,"settings":{"name":null,"title":null,"cs":null,"cs2":null,"left":null,"red":null,"lines":null,"parallels":["1.Цар.31:1"]}},{"index":22,"settings":{"name":null,"title":null,"cs":null,"cs2":null,"left":null,"red":null,"lines":null,"parallels":["1.Цар.14:6"]}},{"index":26,"settings":{"name":null,"title":null,"cs":null,"cs2":null,"left":null,"red":null,"lines":null,"parallels":["2.Цар.9:1","1.Цар.18:1"]}},{"index":11,"settings":{"name":null,"title":null,"cs":null,"cs2":null,"left":null,"red":null,"lines":null,"parallels":["1.Цар.4:12","2.Цар.3:31"]}},{"index":14,"settings":{"name":null,"title":null,"cs":null,"cs2":null,"left":null,"red":null,"lines":null,"parallels":["1.Цар.10:1","1.Цар.24:7","Пс.104:15"]}},{"index":15,"settings":{"name":null,"title":null,"cs":null,"cs2":null,"left":null,"red":null,"lines":null,"parallels":["2.Цар.4:10:12"]}}],"parallels":null}