{"name":"Книга пророка Захарии (Синодальный)","title":false,"cs":false,"cs2":false,"left":true,"red":null,"lines":[{"index":2,"settings":{"name":null,"title":null,"cs":null,"cs2":null,"left":null,"red":null,"lines":null,"parallels":["Зах.12:3","Ис.13:16"]}},{"index":4,"settings":{"name":null,"title":null,"cs":null,"cs2":null,"left":null,"red":null,"lines":null,"parallels":["Деян.1:12"]}},{"index":5,"settings":{"name":null,"title":null,"cs":null,"cs2":null,"left":null,"red":null,"lines":null,"parallels":["2.Пар.26:1","Ам.1:1"]}},{"index":6,"settings":{"name":null,"title":null,"cs":null,"cs2":null,"left":null,"red":null,"lines":null,"parallels":["Мф.24:29"]}},{"index":7,"settings":{"name":null,"title":null,"cs":null,"cs2":null,"left":null,"red":null,"lines":null,"parallels":["Откр.21:23:25","Откр.22:5","Ис.60:20"]}},{"index":8,"settings":{"name":null,"title":null,"cs":null,"cs2":null,"left":null,"red":null,"lines":null,"parallels":["Иез.47:1","Иоил.3:18","Откр.22:1"]}},{"index":9,"settings":{"name":null,"title":null,"cs":null,"cs2":null,"left":null,"red":null,"lines":null,"parallels":["Ис.52:7","Иер.23:5","1.Кор.8:6"]}},{"index":10,"settings":{"name":null,"title":null,"cs":null,"cs2":null,"left":null,"red":null,"lines":null,"parallels":["Зах.8:21-22","Неем.3:6:23","Иер.31:38"]}},{"index":11,"settings":{"name":null,"title":null,"cs":null,"cs2":null,"left":null,"red":null,"lines":null,"parallels":["Ис.33:20","Рим.8:15","Откр.22:3"]}},{"index":12,"settings":{"name":null,"title":null,"cs":null,"cs2":null,"left":null,"red":null,"lines":null,"parallels":["Ис.66:24"]}},{"index":13,"settings":{"name":null,"title":null,"cs":null,"cs2":null,"left":null,"red":null,"lines":null,"parallels":["Ис.3:6"]}},{"index":15,"settings":{"name":null,"title":null,"cs":null,"cs2":null,"left":null,"red":null,"lines":null,"parallels":["Зах.14:12"]}},{"index":16,"settings":{"name":null,"title":null,"cs":null,"cs2":null,"left":null,"red":null,"lines":null,"parallels":["Иез.20:40","Соф.2:11","Зах.8:22"]}},{"index":17,"settings":{"name":null,"title":null,"cs":null,"cs2":null,"left":null,"red":null,"lines":null,"parallels":["Ис.5:6","Ис.60:12","Откр.11:6"]}},{"index":18,"settings":{"name":null,"title":null,"cs":null,"cs2":null,"left":null,"red":null,"lines":null,"parallels":["Ис.5:6"]}},{"index":20,"settings":{"name":null,"title":null,"cs":null,"cs2":null,"left":null,"red":null,"lines":null,"parallels":["3.Цар.7:38"]}},{"index":21,"settings":{"name":null,"title":null,"cs":null,"cs2":null,"left":null,"red":null,"lines":null,"parallels":["Ис.35:8","Иоил.3:17","Откр.21:27","Откр.22:15"]}}],"parallels":null}