{"name":"3я книга Царств (Греческий)","title":false,"cs":false,"cs2":false,"left":true,"red":null,"lines":[{"index":34,"settings":{"name":null,"title":null,"cs":null,"cs2":null,"left":null,"red":null,"lines":null,"parallels":["3.Цар.22:3"]}},{"index":36,"settings":{"name":null,"title":null,"cs":null,"cs2":null,"left":null,"red":null,"lines":null,"parallels":["3.Цар.13:24"]}},{"index":10,"settings":{"name":null,"title":null,"cs":null,"cs2":null,"left":null,"red":null,"lines":null,"parallels":["3.Цар.19:2"]}},{"index":42,"settings":{"name":null,"title":null,"cs":null,"cs2":null,"left":null,"red":null,"lines":null,"parallels":["3.Цар.22:35"]}},{"index":11,"settings":{"name":null,"title":null,"cs":null,"cs2":null,"left":null,"red":null,"lines":null,"parallels":["3.Цар.22:27"]}},{"index":27,"settings":{"name":null,"title":null,"cs":null,"cs2":null,"left":null,"red":null,"lines":null,"parallels":["1.Мак.3:16"]}},{"index":28,"settings":{"name":null,"title":null,"cs":null,"cs2":null,"left":null,"red":null,"lines":null,"parallels":["4.Цар.19:22","Исх.15:3"]}},{"index":13,"settings":{"name":null,"title":null,"cs":null,"cs2":null,"left":null,"red":null,"lines":null,"parallels":["3.Цар.18:4","3.Цар.22:8"]}},{"index":30,"settings":{"name":null,"title":null,"cs":null,"cs2":null,"left":null,"red":null,"lines":null,"parallels":["3.Цар.20:26","3.Цар.22:25","2.Пар.18:24"]}},{"index":31,"settings":{"name":null,"title":null,"cs":null,"cs2":null,"left":null,"red":null,"lines":null,"parallels":["4.Цар.6:26","2.Мак.10:25"]}}],"parallels":null}