{"name":"Евангелие по Луке (Синодальный)","title":false,"cs":false,"cs2":false,"left":true,"red":null,"lines":[{"index":16,"settings":{"name":null,"title":null,"cs":null,"cs2":null,"left":null,"red":null,"lines":null,"parallels":["Притч.9:1-2","Мф.22:2","Откр.19:9"]}},{"index":34,"settings":{"name":null,"title":null,"cs":null,"cs2":null,"left":null,"red":null,"lines":null,"parallels":["Мф.5:13","Мк.9:50"]}},{"index":21,"settings":{"name":null,"title":null,"cs":null,"cs2":null,"left":null,"red":null,"lines":null,"parallels":["Мф.5:3","1.Кор.1:27-28"]}},{"index":8,"settings":{"name":null,"title":null,"cs":null,"cs2":null,"left":null,"red":null,"lines":null,"parallels":["Притч.25:6"]}},{"index":24,"settings":{"name":null,"title":null,"cs":null,"cs2":null,"left":null,"red":null,"lines":null,"parallels":["Мф.22:8"]}},{"index":26,"settings":{"name":null,"title":null,"cs":null,"cs2":null,"left":null,"red":null,"lines":null,"parallels":["Мф.10:37"]}},{"index":11,"settings":{"name":null,"title":null,"cs":null,"cs2":null,"left":null,"red":null,"lines":null,"parallels":["Мф.23:12","Лк.18:14"]}},{"index":27,"settings":{"name":null,"title":null,"cs":null,"cs2":null,"left":null,"red":null,"lines":null,"parallels":["Мф.10:38","Мф.16:24","Мк.8:34","Лк.9:23","2.Тим.3:12"]}},{"index":12,"settings":{"name":null,"title":null,"cs":null,"cs2":null,"left":null,"red":null,"lines":null,"parallels":["Тов.4:7","Притч.3:27-28"]}}],"parallels":null}