{"name":"Левит (Синодальный)","title":false,"cs":false,"cs2":false,"left":true,"red":null,"lines":[{"index":2,"settings":{"name":null,"title":null,"cs":null,"cs2":null,"left":null,"red":null,"lines":null,"parallels":["Исх.28:1","Лев.9:18:22"]}},{"index":35,"settings":{"name":null,"title":null,"cs":null,"cs2":null,"left":null,"red":null,"lines":null,"parallels":["Лев.10:7"]}},{"index":6,"settings":{"name":null,"title":null,"cs":null,"cs2":null,"left":null,"red":null,"lines":null,"parallels":["Исх.28:1","Исх.40:12"]}},{"index":10,"settings":{"name":null,"title":null,"cs":null,"cs2":null,"left":null,"red":null,"lines":null,"parallels":["Исх.30:25","Чис.7:1"]}},{"index":12,"settings":{"name":null,"title":null,"cs":null,"cs2":null,"left":null,"red":null,"lines":null,"parallels":["Исх.29:7","Чис.35:25","Пс.132:2","Сир.45:18"]}},{"index":14,"settings":{"name":null,"title":null,"cs":null,"cs2":null,"left":null,"red":null,"lines":null,"parallels":["Исх.29:10"]}},{"index":15,"settings":{"name":null,"title":null,"cs":null,"cs2":null,"left":null,"red":null,"lines":null,"parallels":["2.Пар.29:22","Исх.29:16"]}},{"index":16,"settings":{"name":null,"title":null,"cs":null,"cs2":null,"left":null,"red":null,"lines":null,"parallels":["Лев.3:4"]}},{"index":18,"settings":{"name":null,"title":null,"cs":null,"cs2":null,"left":null,"red":null,"lines":null,"parallels":["Исх.29:15"]}},{"index":21,"settings":{"name":null,"title":null,"cs":null,"cs2":null,"left":null,"red":null,"lines":null,"parallels":["Исх.29:18","Лев.1:9"]}},{"index":22,"settings":{"name":null,"title":null,"cs":null,"cs2":null,"left":null,"red":null,"lines":null,"parallels":["Исх.29:19"]}},{"index":23,"settings":{"name":null,"title":null,"cs":null,"cs2":null,"left":null,"red":null,"lines":null,"parallels":["Лев.14:14"]}},{"index":25,"settings":{"name":null,"title":null,"cs":null,"cs2":null,"left":null,"red":null,"lines":null,"parallels":["Исх.29:22"]}},{"index":26,"settings":{"name":null,"title":null,"cs":null,"cs2":null,"left":null,"red":null,"lines":null,"parallels":["Исх.29:23"]}},{"index":28,"settings":{"name":null,"title":null,"cs":null,"cs2":null,"left":null,"red":null,"lines":null,"parallels":["Лев.1:9"]}},{"index":29,"settings":{"name":null,"title":null,"cs":null,"cs2":null,"left":null,"red":null,"lines":null,"parallels":["Исх.29:24","Лев.7:33"]}},{"index":30,"settings":{"name":null,"title":null,"cs":null,"cs2":null,"left":null,"red":null,"lines":null,"parallels":["Исх.29:21","Сир.45:18"]}},{"index":31,"settings":{"name":null,"title":null,"cs":null,"cs2":null,"left":null,"red":null,"lines":null,"parallels":["Исх.29:32","Лев.24:9","Мф.12:4","Мк.2:26","Лк.6:4"]}}],"parallels":null}