{"name":"Книга пророка Иеремии (Еврейский)","title":false,"cs":false,"cs2":false,"left":false,"red":null,"lines":[{"index":1,"settings":{"name":null,"title":null,"cs":null,"cs2":null,"left":null,"red":null,"lines":null,"parallels":["Деян.21:11"]}},{"index":9,"settings":{"name":null,"title":null,"cs":null,"cs2":null,"left":null,"red":null,"lines":null,"parallels":["4.Цар.24:2"]}},{"index":10,"settings":{"name":null,"title":null,"cs":null,"cs2":null,"left":null,"red":null,"lines":null,"parallels":["Иер.11:8","Иер.22:21","Вар.1:22"]}},{"index":11,"settings":{"name":null,"title":null,"cs":null,"cs2":null,"left":null,"red":null,"lines":null,"parallels":["Втор.26:19"]}},{"index":14,"settings":{"name":null,"title":null,"cs":null,"cs2":null,"left":null,"red":null,"lines":null,"parallels":["Иер.16:5"]}},{"index":15,"settings":{"name":null,"title":null,"cs":null,"cs2":null,"left":null,"red":null,"lines":null,"parallels":["Иак.1:21"]}},{"index":16,"settings":{"name":null,"title":null,"cs":null,"cs2":null,"left":null,"red":null,"lines":null,"parallels":["Нав.7:19","Ин.9:24","Ис.59:9"]}},{"index":17,"settings":{"name":null,"title":null,"cs":null,"cs2":null,"left":null,"red":null,"lines":null,"parallels":["Плач.1:2:16"]}},{"index":18,"settings":{"name":null,"title":null,"cs":null,"cs2":null,"left":null,"red":null,"lines":null,"parallels":["Ис.47:1","Плач.5:16"]}},{"index":20,"settings":{"name":null,"title":null,"cs":null,"cs2":null,"left":null,"red":null,"lines":null,"parallels":["Иер.1:14"]}},{"index":21,"settings":{"name":null,"title":null,"cs":null,"cs2":null,"left":null,"red":null,"lines":null,"parallels":["Иер.6:24"]}},{"index":22,"settings":{"name":null,"title":null,"cs":null,"cs2":null,"left":null,"red":null,"lines":null,"parallels":["Иер.5:19","Иер.30:15"]}},{"index":27,"settings":{"name":null,"title":null,"cs":null,"cs2":null,"left":null,"red":null,"lines":null,"parallels":["Иер.5:8"]}}],"parallels":null}