{"name":"Книга пророка Даниила (Еврейский)","title":false,"cs":false,"cs2":false,"left":false,"red":null,"lines":[{"index":1,"settings":{"name":null,"title":null,"cs":null,"cs2":null,"left":null,"red":null,"lines":null,"parallels":["Агг.1:1","Дан.5:31"]}},{"index":2,"settings":{"name":null,"title":null,"cs":null,"cs2":null,"left":null,"red":null,"lines":null,"parallels":["1.Езд.1:1","2.Пар.36:22","Иер.25:12","Иер.29:10"]}},{"index":4,"settings":{"name":null,"title":null,"cs":null,"cs2":null,"left":null,"red":null,"lines":null,"parallels":["Исх.20:6","Втор.7:9","Неем.1:5","Неем.9:32"]}},{"index":5,"settings":{"name":null,"title":null,"cs":null,"cs2":null,"left":null,"red":null,"lines":null,"parallels":["Пс.105:6","Вар.1:17","Вар.2:12"]}},{"index":6,"settings":{"name":null,"title":null,"cs":null,"cs2":null,"left":null,"red":null,"lines":null,"parallels":["Иер.44:16"]}},{"index":7,"settings":{"name":null,"title":null,"cs":null,"cs2":null,"left":null,"red":null,"lines":null,"parallels":["Пс.144:17","Иер.9:24","Вар.1:15"]}},{"index":8,"settings":{"name":null,"title":null,"cs":null,"cs2":null,"left":null,"red":null,"lines":null,"parallels":["Неем.9:34","Иер.2:26","Иер.3:25"]}},{"index":9,"settings":{"name":null,"title":null,"cs":null,"cs2":null,"left":null,"red":null,"lines":null,"parallels":["Пс.129:4","Лк.1:72"]}},{"index":10,"settings":{"name":null,"title":null,"cs":null,"cs2":null,"left":null,"red":null,"lines":null,"parallels":["2.Пар.36:15","Соф.3:2"]}},{"index":11,"settings":{"name":null,"title":null,"cs":null,"cs2":null,"left":null,"red":null,"lines":null,"parallels":["Втор.28:15","Плач.2:17","Вар.1:20","Мал.2:2"]}},{"index":12,"settings":{"name":null,"title":null,"cs":null,"cs2":null,"left":null,"red":null,"lines":null,"parallels":["Вар.2:1"]}},{"index":14,"settings":{"name":null,"title":null,"cs":null,"cs2":null,"left":null,"red":null,"lines":null,"parallels":["Пс.144:17"]}},{"index":15,"settings":{"name":null,"title":null,"cs":null,"cs2":null,"left":null,"red":null,"lines":null,"parallels":["Исх.12:41","Вар.2:11"]}},{"index":16,"settings":{"name":null,"title":null,"cs":null,"cs2":null,"left":null,"red":null,"lines":null,"parallels":["Вар.2:13"]}},{"index":18,"settings":{"name":null,"title":null,"cs":null,"cs2":null,"left":null,"red":null,"lines":null,"parallels":["Вар.2:17"]}},{"index":21,"settings":{"name":null,"title":null,"cs":null,"cs2":null,"left":null,"red":null,"lines":null,"parallels":["Дан.8:16"]}},{"index":23,"settings":{"name":null,"title":null,"cs":null,"cs2":null,"left":null,"red":null,"lines":null,"parallels":["1.Езд.6:14","Дан.10:12"]}},{"index":24,"settings":{"name":null,"title":null,"cs":null,"cs2":null,"left":null,"red":null,"lines":null,"parallels":["Иер.23:5","Иез.37:25"]}},{"index":25,"settings":{"name":null,"title":null,"cs":null,"cs2":null,"left":null,"red":null,"lines":null,"parallels":["1.Езд.6:14","Лк.7:19"]}},{"index":26,"settings":{"name":null,"title":null,"cs":null,"cs2":null,"left":null,"red":null,"lines":null,"parallels":["Ис.53:8","Мф.24:2","Дан.11:10"]}},{"index":27,"settings":{"name":null,"title":null,"cs":null,"cs2":null,"left":null,"red":null,"lines":null,"parallels":["Мф.24:15","Мк.13:14","Лк.21:20"]}}],"parallels":null}